{
  "strategy_name": "HyperTuned_SR_ST_W15_2D_D270_S2_EQ",
  "data_requirements": {
    "min_data_days": 270,
    "skip_first_n_days": 2
  },
  "factors": [
    {
      "function": "calculate_sharpe_ratio",
      "params": {
        "window": 15,
        "input_column": "roi_2d"
      }
    },
    {
      "function": "calculate_inv_std_dev",
      "params": {
        "window": 15,
        "input_column": "roi_2d"
      }
    }
  ],
  "scoring": {
    "method": "equal",
    "weights": "auto"
  }
}