{
  "strategy_id": "SR_WR_W60_1D_D60_S1_EQ",
  "strategy_config": {
    "strategy_id": "SR_WR_W60_1D_D60_S1_EQ",
    "strategy_name": "HyperTuned_SR_WR_W60_1D_D60_S1_EQ",
    "data_requirements": {
      "min_data_days": 60,
      "skip_first_n_days": 1
    },
    "factors": [
      {
        "function": "calculate_sharpe_ratio",
        "window": 60,
        "input_column": "roi_1d"
      },
      {
        "function": "calculate_win_rate",
        "window": 60,
        "input_column": "roi_1d"
      }
    ],
    "scoring": {
      "method": "equal",
      "weights": "auto"
    },
    "metadata": {
      "generated_at": "2025-07-01T15:56:32.936414",
      "generator_version": "1.0",
      "total_factors": 2,
      "window": 60,
      "input_column": "roi_1d"
    }
  },
  "ranking_result": {
    "strategy_name": "SR_WR_W60_1D_D60_S1_EQ",
    "start_date": "2025-06-01",
    "end_date": "2025-06-07",
    "total_days": 7,
    "successful_days": 7,
    "success_rate": 100.0
  },
  "backtest_result": {
    "strategy_id": "SR_WR_W60_1D_D60_S1_EQ",
    "strategy_name": "SR_WR_W60_1D_D60_S1_EQ",
    "start_date": "2025-06-01",
    "end_date": "2025-06-07",
    "initial_capital": 10000,
    "final_capital": 10000,
    "total_return": 0,
    "roi": 0.0,
    "max_drawdown": 0.0,
    "sharpe_ratio": 0.0,
    "win_rate": 0.0,
    "total_trades": 0,
    "avg_holding_days": 0.0,
    "backtest_days": 7,
    "status": "completed"
  },
  "execution_time": "2025-07-01T15:56:38.410284"
}